kubeflow/__init__.py
kubeflow/storage_initializer/__init__.py
kubeflow/storage_initializer/abstract_dataset_provider.py
kubeflow/storage_initializer/abstract_model_provider.py
kubeflow/storage_initializer/constants.py
kubeflow/storage_initializer/hugging_face.py
kubeflow/storage_initializer/s3.py
kubeflow/storage_initializer/storage.py
kubeflow/training/__init__.py
kubeflow/training/api_client.py
kubeflow/training/configuration.py
kubeflow/training/exceptions.py
kubeflow/training/rest.py
kubeflow/training/api/__init__.py
kubeflow/training/api/training_client.py
kubeflow/training/api/training_client_test.py
kubeflow/training/constants/__init__.py
kubeflow/training/constants/constants.py
kubeflow/training/models/__init__.py
kubeflow/training/models/kubeflow_org_v1_elastic_policy.py
kubeflow/training/models/kubeflow_org_v1_jax_job.py
kubeflow/training/models/kubeflow_org_v1_jax_job_list.py
kubeflow/training/models/kubeflow_org_v1_jax_job_spec.py
kubeflow/training/models/kubeflow_org_v1_job_condition.py
kubeflow/training/models/kubeflow_org_v1_job_status.py
kubeflow/training/models/kubeflow_org_v1_mpi_job.py
kubeflow/training/models/kubeflow_org_v1_mpi_job_list.py
kubeflow/training/models/kubeflow_org_v1_mpi_job_spec.py
kubeflow/training/models/kubeflow_org_v1_paddle_elastic_policy.py
kubeflow/training/models/kubeflow_org_v1_paddle_job.py
kubeflow/training/models/kubeflow_org_v1_paddle_job_list.py
kubeflow/training/models/kubeflow_org_v1_paddle_job_spec.py
kubeflow/training/models/kubeflow_org_v1_py_torch_job.py
kubeflow/training/models/kubeflow_org_v1_py_torch_job_list.py
kubeflow/training/models/kubeflow_org_v1_py_torch_job_spec.py
kubeflow/training/models/kubeflow_org_v1_rdzv_conf.py
kubeflow/training/models/kubeflow_org_v1_replica_spec.py
kubeflow/training/models/kubeflow_org_v1_replica_status.py
kubeflow/training/models/kubeflow_org_v1_run_policy.py
kubeflow/training/models/kubeflow_org_v1_scheduling_policy.py
kubeflow/training/models/kubeflow_org_v1_tf_job.py
kubeflow_training-1.9.3.dist-info/METADATA
kubeflow_training-1.9.3.dist-info/WHEEL
kubeflow_training-1.9.3.dist-info/top_level.txt
kubeflow_training-1.9.3.dist-info/RECORD
