Metadata-Version: 2.4
Name: kubeflow-training
Version: 1.9.3
Summary: Training Operator Python SDK
Home-page: https://github.com/kubeflow/training-operator/tree/master/sdk/python
Author: Kubeflow Authors
Author-email: hejinchi@cn.ibm.com
License: Apache License Version 2.0
Classifier: Intended Audience :: Developers
Classifier: Intended Audience :: Education
Classifier: Intended Audience :: Science/Research
Classifier: Programming Language :: Python :: 3.8
Classifier: Programming Language :: Python :: 3.9
Classifier: Programming Language :: Python :: 3.10
Classifier: Programming Language :: Python :: 3.11
Classifier: License :: OSI Approved :: Apache Software License
Classifier: Operating System :: OS Independent
Classifier: Topic :: Scientific/Engineering
Classifier: Topic :: Scientific/Engineering :: Artificial Intelligence
Classifier: Topic :: Software Development
Classifier: Topic :: Software Development :: Libraries
Classifier: Topic :: Software Development :: Libraries :: Python Modules
Requires-Dist: certifi>=14.05.14
Requires-Dist: six>=1.10
Requires-Dist: setuptools>=21.0.0
Requires-Dist: urllib3>=1.15.1
Requires-Dist: kubernetes>=27.2.0
Requires-Dist: retrying>=1.3.3
Provides-Extra: test
Requires-Dist: pytest; extra == "test"
Requires-Dist: pytest-tornasync; extra == "test"
Requires-Dist: mypy; extra == "test"
Requires-Dist: black==24.3.0; extra == "test"
Requires-Dist: flake8==4.0.1; extra == "test"
Provides-Extra: huggingface
Requires-Dist: transformers==4.50.2; extra == "huggingface"
Requires-Dist: peft==0.15.1; extra == "huggingface"
Dynamic: author
Dynamic: author-email
Dynamic: classifier
Dynamic: description
Dynamic: home-page
Dynamic: license
Dynamic: provides-extra
Dynamic: requires-dist
Dynamic: summary
